{
	"info": {
		"_postman_id": "5a275652-d413-4793-86fa-06330205e93d",
		"name": "SI 52 - Nathalia Margaretha",
		"description": "### Welcome to Postman! This is your first collection. \n\nCollections are your starting point for building and testing APIs. You can use this one to:\n\n• Group related requests\n• Test your API in real-world scenarios\n• Document and share your requests\n\nUpdate the name and overview whenever you’re ready to make it yours.\n\n[Learn more about Postman Collections.](https://learning.postman.com/docs/collections/collections-overview/)",
		"schema": "https://schema.getpostman.com/json/collection/v2.1.0/collection.json",
		"_exporter_id": "49362346",
		"_collection_link": "https://nathaliamargaretha2506-8014388.postman.co/workspace/Nathalia-Margaretha's-Workspace~c7804b1f-7ba6-45d7-8b73-f989839472b7/collection/49362346-5a275652-d413-4793-86fa-06330205e93d?action=share&source=collection_link&creator=49362346"
	},
	"item": [
		{
			"name": "register",
			"event": [
				{
					"listen": "test",
					"script": {
						"exec": [
							"pm.test(\"Status code is 200\", function () {",
							"    pm.response.to.have.status(200);",
							"});"
						],
						"type": "text/javascript",
						"packages": {},
						"requests": {}
					}
				}
			],
			"request": {
				"method": "POST",
				"header": [
					{
						"key": "Accept",
						"value": "application/json",
						"type": "text"
					}
				],
				"body": {
					"mode": "raw",
					"raw": "{\r\n    \"username\" : \"nathaliamargaretha2\",\r\n    \"email\" : \"nathalia2@gmail.com\",\r\n    \"password\" : \"12345678\"\r\n}",
					"options": {
						"raw": {
							"language": "json"
						}
					}
				},
				"url": {
					"raw": "http://localhost:3000/api/register",
					"protocol": "http",
					"host": [
						"localhost"
					],
					"port": "3000",
					"path": [
						"api",
						"register"
					]
				},
				"description": "This is a GET request and it is used to \"get\" data from an endpoint. There is no request body for a GET request, but you can use query parameters to help specify the resource you want data on (e.g., in this request, we have `id=1`).\n\nA successful GET response will have a `200 OK` status, and should include some kind of response body - for example, HTML web content or JSON data."
			},
			"response": []
		},
		{
			"name": "login",
			"event": [
				{
					"listen": "test",
					"script": {
						"exec": [
							"pm.test(\"Successful POST request\", function () {",
							"    pm.expect(pm.response.code).to.be.oneOf([200, 201]);",
							"});",
							""
						],
						"type": "text/javascript",
						"packages": {},
						"requests": {}
					}
				}
			],
			"request": {
				"method": "POST",
				"header": [
					{
						"key": "Accept",
						"value": "application/json",
						"type": "text"
					}
				],
				"body": {
					"mode": "raw",
					"raw": "{\n    \"username\" : \"nathaliamargaretha2\",\n    \"email\" : \"nathalia2@gmail.com\",\n    \"password\" : \"12345678\"\n}",
					"options": {
						"raw": {
							"language": "json"
						}
					}
				},
				"url": {
					"raw": "http://localhost:3000/api/login",
					"protocol": "http",
					"host": [
						"localhost"
					],
					"port": "3000",
					"path": [
						"api",
						"login"
					]
				},
				"description": "This is a POST request, submitting data to an API via the request body. This request submits JSON data, and the data is reflected in the response.\n\nA successful POST request typically returns a `200 OK` or `201 Created` response code."
			},
			"response": []
		},
		{
			"name": "List Destinasi Wisata",
			"protocolProfileBehavior": {
				"disableBodyPruning": true
			},
			"request": {
				"method": "GET",
				"header": [
					{
						"key": "Accept",
						"value": "application/json",
						"type": "text"
					}
				],
				"body": {
					"mode": "raw",
					"raw": "{\r\n\t\"destination\": \"Eiffel Tower\",\r\n    \"country\": \"Paris, France\",\r\n    \"reason\": \"Icon of Paris\"\r\n}",
					"options": {
						"raw": {
							"language": "json"
						}
					}
				},
				"url": {
					"raw": "http://localhost:3000/api/destinasi_wisata",
					"protocol": "http",
					"host": [
						"localhost"
					],
					"port": "3000",
					"path": [
						"api",
						"destinasi_wisata"
					]
				}
			},
			"response": []
		},
		{
			"name": "Create Destinasi Wisata",
			"request": {
				"method": "POST",
				"header": [
					{
						"key": "Accept",
						"value": "application/json",
						"type": "text"
					}
				],
				"body": {
					"mode": "raw",
					"raw": "{\r\n\t\"destination\": \"Eiffel Tower\",\r\n    \"country\": \"Paris, France\",\r\n    \"reason\": \"Icon of Paris\"\r\n}",
					"options": {
						"raw": {
							"language": "json"
						}
					}
				},
				"url": {
					"raw": "http://localhost:3000/api/destinasi_wisata",
					"protocol": "http",
					"host": [
						"localhost"
					],
					"port": "3000",
					"path": [
						"api",
						"destinasi_wisata"
					]
				}
			},
			"response": []
		},
		{
			"name": "Update Destinasi Wisata",
			"request": {
				"method": "PUT",
				"header": [
					{
						"key": "Accept",
						"value": "application/json",
						"type": "text"
					}
				],
				"body": {
					"mode": "raw",
					"raw": "{\r\n\t\"destination\": \"Eiffel Tower\",\r\n    \"country\": \"Paris, France\",\r\n    \"reason\": \"Icon of Paris, Locals Favorite's Place\"\r\n}",
					"options": {
						"raw": {
							"language": "json"
						}
					}
				},
				"url": {
					"raw": "http://localhost:3000/api/destinasi_wisata/68fcf68e2481a852ac1d2d45",
					"protocol": "http",
					"host": [
						"localhost"
					],
					"port": "3000",
					"path": [
						"api",
						"destinasi_wisata",
						"68fcf68e2481a852ac1d2d45"
					]
				}
			},
			"response": []
		},
		{
			"name": "Delete Destinasi Wisata",
			"request": {
				"method": "DELETE",
				"header": [
					{
						"key": "Accept",
						"value": "application/json",
						"type": "text"
					}
				],
				"body": {
					"mode": "raw",
					"raw": "{\r\n\t\"destination\": \"Eiffel Tower\",\r\n    \"country\": \"Paris, France\",\r\n    \"reason\": \"Icon of Paris\"\r\n}",
					"options": {
						"raw": {
							"language": "json"
						}
					}
				},
				"url": {
					"raw": "http://localhost:3000/api/destinasi_wisata/68fcf68e2481a852ac1d2d45",
					"protocol": "http",
					"host": [
						"localhost"
					],
					"port": "3000",
					"path": [
						"api",
						"destinasi_wisata",
						"68fcf68e2481a852ac1d2d45"
					]
				}
			},
			"response": []
		},
		{
			"name": "me",
			"protocolProfileBehavior": {
				"disableBodyPruning": true
			},
			"request": {
				"method": "GET",
				"header": [
					{
						"key": "Accept",
						"value": "application/json",
						"type": "text"
					},
					{
						"key": "Authorization",
						"value": "Bearer eyJhbGciOiJIUzI1NiIsInR5cCI6IkpXVCJ9.eyJ1c2VybmFtZSI6Im5hdGhhbGlhbWFyZ2FyZXRoYTIiLCJlbWFpbCI6Im5hdGhhbGlhMkBnbWFpbC5jb20iLCJpYXQiOjE3NjE0MDkxNjEsImV4cCI6MTc2MTQxMjc2MX0.emQQ8_MjEa-R5aKxW2vufu57c1IBUVw6RAX8ajn5x80",
						"type": "text"
					}
				],
				"body": {
					"mode": "raw",
					"raw": "{\r\n    \"username\" : \"nathaliamargaretha1\",\r\n    \"email\" : \"nathalia1@gmail.com\",\r\n    \"password\" : \"12345678\"\r\n}",
					"options": {
						"raw": {
							"language": "json"
						}
					}
				},
				"url": {
					"raw": "http://localhost:3000/api/me",
					"protocol": "http",
					"host": [
						"localhost"
					],
					"port": "3000",
					"path": [
						"api",
						"me"
					]
				}
			},
			"response": []
		}
	]
}